ipyclipboard/__about__.py
ipyclipboard/__init__.py
ipyclipboard/static/widget.css
ipyclipboard/static/widget.js
ipyclipboard-0.0.1.dist-info/METADATA
ipyclipboard-0.0.1.dist-info/WHEEL
ipyclipboard-0.0.1.dist-info/RECORD
